cerber/__init__.py
cerber/tests/__init__.py
cerber/tests/test_cerber.py
cerber-0.3.0.dist-info/DESCRIPTION.rst
cerber-0.3.0.dist-info/METADATA
cerber-0.3.0.dist-info/RECORD
cerber-0.3.0.dist-info/WHEEL
cerber-0.3.0.dist-info/entry_points.txt
cerber-0.3.0.dist-info/metadata.json
cerber-0.3.0.dist-info/pbr.json
cerber-0.3.0.dist-info/top_level.txt
