Metadata-Version: 2.0
Name: cerber
Version: 0.3.0
Summary: Command line tool to generate secure computing mode
Home-page: https://github.com/gr0und-s3ct0r/cerber/
Author: gr0und-s3ct0r
Author-email: contact@groundsector.com
License: UNKNOWN
Platform: UNKNOWN
Classifier: Intended Audience :: Information Technology
Classifier: License :: OSI Approved :: MIT License
Classifier: Operating System :: POSIX
Classifier: Programming Language :: Python
Classifier: Programming Language :: Python :: 3
Classifier: Programming Language :: Python :: 3.5
Classifier: Programming Language :: Python :: 3.6
Requires: pbd
Provides-Extra: test
Requires-Dist: fixtures; extra == 'test'
Requires-Dist: tox; extra == 'test'
